{"name_zh": "复仇者联盟4：终局之战", "name_en": "Avengers: Endgame", "categorys": ["动作", "冒险", "奇幻"], "area": "美国", "duration": "181分钟", "date": "2019-04-24中国大陆上映", "awards": ["第92届奥斯卡金像奖", "第73届英国电影学院奖", "第92届奥斯卡金像奖", "第73届英国电影学院奖", "第47届安妮奖", "第28届MTV电影奖", "第25届评论家选择奖", "第26届美国演员工会奖", "第18届华盛顿影评人协会奖", "第24届美国艺术指导工会奖", "第32届芝加哥影评人协会奖", "第22届美国服装设计工会奖", "第7届美国化妆及发型设计工会奖", "第67届美国音效剪辑协会奖", "第18届美国视觉效果协会奖", "第24届金卫星奖", "第2届金众电影青年"], "director": "乔·罗素", "actors": ["安东尼·罗素", "小罗伯特·唐尼", "克里斯·埃文斯", "马克·鲁法洛", "乔·罗素", "安东尼·罗素", "小罗伯特·唐尼", "克里斯·埃文斯", "马克·鲁法洛", "克里斯·海姆斯沃斯", "斯嘉丽·约翰逊", "杰瑞米·雷纳", "唐·钱德尔", "保罗·路德", "布丽·拉尔森", "凯伦·吉兰", "泰莎·汤普森", "达娜·贾克赛·古瑞拉", "本尼迪特·王", "乔恩·费儒", "格温妮斯·帕特洛", "乔什·布洛林", "本尼迪克特·康伯巴奇", "佐伊·索尔达娜", "克里斯·帕拉特", "安东尼·麦凯", "伊丽莎白·奥尔森", "伊万杰琳•莉莉", "汤姆·赫兰德", "蕾妮·罗素", "约翰·斯拉特里", "查德维克·博斯曼", "塞巴斯蒂安·斯坦", "汤姆·希德勒斯顿", "戴夫·巴蒂斯塔", "利蒂希娅·赖特", "庞·克莱门捷夫", "范·迪塞尔", "蒂尔达·斯文顿", "弗兰克·格里罗", "塞缪尔·杰克逊", "娜塔莉·波特曼", "米歇尔·菲佛", "玛丽莎·托梅", "塔伊加·维迪提", "安吉拉·贝塞特", "迈克尔·道格拉斯", "威廉·赫特", "寇碧·史莫德斯", "肖恩·古恩", "琳达·卡德里尼", "马克斯米利亚诺·赫尔南德斯", "真田广之", "汤姆·沃恩-劳勒", "泰瑞·诺塔里", "詹姆斯·达西", "雅各·巴塔伦", "罗伯特·雷德福", "泰·辛普金斯", "温斯顿·杜克", "斯坦·李", "Justin Slaughter", "Brandon Rush", "Jaylen Davis", "莱蒂希娅·米歇尔·赖特", "布莱德利·库珀", "凯瑞·康顿", "闻天", "伊薇特·尼科尔·布朗", "Cameron Brumbelow", "蒂莫西·卡尔", "迈克尔·A·库克", "凯莉·库恩", "艾玛·福尔曼", "雷纳·加拉赫", "Daniela Gaskie", "郑肯", "小弗洛伊德·安东尼·约翰", "罗斯·马昆德", "布伦特·麦吉", "Michael Pierino Miller", "卡兰·穆尔韦", "吉米·雷·皮肯斯", "迈克尔·詹姆斯·肖", "Greg Tiffan", "艾娃·罗素", "乔·罗素", "玛丽亚·Z·威尔逊", "本杰明·韦弗", "Raul Alcantar", "雅各布·埃文斯", "何塞·阿尔弗雷多·费尔南德斯", "布伦特·莫雷尔·加斯金斯", "安东尼·B·哈里斯", "Shaun McMillan", "Robert Payen", "麦克斯威尔·海史密斯", "罗伯特·廷斯利", "费斯·洛根", "Paul Pillsbury", "特拉维斯·汤普森", "亚历珊德拉‧瑞秋·拉贝", "贾迈尔·钱伯斯", "Jennifer Cain", "杰克逊·艾顿", "布莱德利·库珀", "凯瑟琳·兰福德", "亚历山德拉·蕾切尔·拉贝", "海莉·阿特维尔", "凯瑞·康顿", "麦克斯米利安诺·贺南德兹", "莫妮卡·甘德顿", "基思·努斯鲍姆", "Timothy Carr", "Khalid Ghajji", "Eric Wallace", "Hyejin J.", "史蒂文·艾萨尼", "罗伯特·普拉格", "布莱恩·谢弗", "艾米丽塔·T·冈萨雷斯", "凯德·伍德沃德", "Taylor Patterson", "帕特里克·高曼", "艾米娜·卡普兰", "阿隆·拉扎尔", "迈克·卢茨", "Olaniyan Thurmon", "Russell Bobbitt", "Lee Moore", "乔依·麦卡沃伊", "约翰·波西", "Ben Sakamoto", "John Michael Morris", "吉姆·斯特林", "Hye Jin Jang", "James Lin", "山姆·哈格雷夫", "汤姆·威斯多姆", "Ameenah Kaplan", "杰克·科比", "克里斯托弗·马库斯", "斯蒂芬·麦克菲利", "吉姆·斯特林", "斯坦·李", "乔·西蒙", "史蒂夫·恩格尔哈特", "史蒂夫·甘", "Bill Mantlo", "基思·吉芬", "拉里·利伯", "唐·赫克", "凯文·费奇", "米切尔·贝尔", "克里斯托弗·马库斯", "斯蒂芬·麦克菲利", "乔恩·费儒", "詹姆斯·古恩", "斯坦·李", "维多利亚·阿隆索", "陈贞", "路易斯·德·埃斯波西托", "Ari Costa", "乔安·佩里塔诺", "Edu Sallouti", "Nicholas Simon", "Jen Underdahl", "特伦特·欧派洛克", "马修·施密特", "杰弗里·福特", "特伦特·欧派洛克", "Agata Maliauka", "查尔斯·伍德", "Jerad Marantz", "朱利安·阿什比", "Ray Chan", "詹恩·K·恩格尔", "比特·弗鲁蒂格", "Kevin Gilbert", "迈克·斯塔利昂", "萨拉·芬兰", "杰弗里·福特", "马修·施密特", "柯克·A·詹金斯", "James Lin", "Chris Cloud", "Leila Nurse", "Ted Alvarez", "Trey Neely", "戴夫‧乔丹", "亚伦·史维斯查", "Jonathan Bartz", "Thomas Bowes", "皮特·科宾", "Grace Davidson", "戴夫‧乔丹", "Edie Lehmann", "London Voices", "麦罗佛", "Jon Mattox", "Perry Montague Mason", "The Newton Brothers", "马克·皮崔", "丹尼斯·S·桑兹", "亚伦·史维斯查", "James Thatcher", "基尔斯蒂·瓦利", "Chris Castaldi", "丹·德里伍", "山姆·哈格雷夫", "海伦娜·福尔摩斯", "Jeff Okabayashi", "约瑟夫·莱迪", "大卫·萨迪", "查尔斯·伍德", "Bill Myer", "玛丽‧卡斯特", "朱迪安娜·马科夫斯基", "玛丽‧卡斯特", "萨拉·芬兰", "塔伊加·维迪提", "维多利亚·阿隆索", "杰弗里·福特", "特伦特·欧派洛克", "布莱德利·库珀", "米切尔·贝尔", "马修·施密特", "薇薇安·贝克", "凯瑞·康顿", "Ari Costa", "范·迪塞尔", "路易斯·德·埃斯波西托", "乔恩·费儒", "Jennifer Bell", "凯文·费奇", "迈克尔·格里洛", "约翰·布雷克", "詹姆斯·古恩", "斯坦·李", "克里斯托弗·马库斯", "斯蒂芬·麦克菲利", "乔安·佩里塔诺", "Edu Sallouti", "Nicholas Simon", "陈贞", "Jen Underdahl", "劳拉·丹德里奇", "黛博拉·拉·米亚·德内弗", "Alexei O'Brien", "Andrea Finch", "Robin Fredriksz", "杰克·加伯", "Tim Hays", "Will Huff", "Tracey Levy", "Dennis Liddiard", "Frances Mathias", "Bart Mixon", "克里斯托弗", "道格拉斯·诺亚", "瓦利·奥雷利", "芭芭拉·奥尔维拉", "Francisco X. Pérez", "比约恩·雷贝恩", "Sian Richards", "金·桑坦托尼奥", "Matteo Silvi", "海巴·索里斯多蒂尔", "Peter Tothpal", "克林顿·维恩", "Jay Wejebe", "Kelly Zak", "Brittany Horn", "Bill Myer", "Deborah Patino Rutherford", "Christopher 'Critter' Antonucci", "Jane Oshita", "丹·德里伍", "特伦特·牛顿", "瑞秋·劳伦森", "格雷格·赫尔曼", "丹尼·冈萨雷斯", "卡迪尔·坎·埃克西", "简·菲利普·克雷默", "斯科特·埃德斯坦", "陈安伟", "詹森·拉尼尔·布朗", "布莱恩·J·阿尔瓦雷斯", "卡洛斯·华达德", "米格尔·A·萨莱克", "托马斯·尼特曼", "瑞恩·赫斯蒂斯", "罗恩·安德达尔", "艾米丽·尼采", "大卫·范塔塞尔", "斯托恩·尼伦", "汉娜·龙", "温·李拉桑塔纳", "Chris Castaldi", "朱利安·阿什比", "朱迪安娜·马科夫斯基", "查尔斯·伍德", "莱斯利·波普", "大卫·J·巴克", "Beverly Abbott", "詹姆斯·阿邦纳瓦斯", "David Boucher", "詹恩·K·恩格尔", "比特·弗鲁蒂格", "Jim Charmatz", "山姆·哈格雷夫", "Kevin Gilbert", "布赖恩·阿德勒", "迈克·斯塔利昂", "大卫·法默", "Jeff Okabayashi", "达米安·费舍尔", "约瑟夫·莱迪", "Josh Gold", "马特·艾特肯", "大卫·萨迪", "Scott Hinkley", "林赛·麦克戈温", "尚恩·马翰", "Daniel Laurie", "詹姆斯·利考斯基", "乔什·洛森", "Brian Long", "瑞安·艾伦", "Jon Allitt", "香农·米尔斯", "Rob Allman", "丹尼尔·萨迪克", "丹·奥康奈尔", "李·奥尔洛夫", "Bryan Pennington", "Juan Peralta", "约翰·普里切特", "Christine Arboit", "布莱恩·桑德斯", "保罗·阿里昂", "麦克·史密斯", "卢克·阿姆斯特朗", "丹·阿什顿", "Vic Kaspar", "William Barkus", "Pharoah Barrett", "Graham Binding", "Adam Blank", "杰米·布莱斯", "Draghici Bogdan", "Steve Braggs", "Dhiraj Brahma", "Paul Brannan", "罗布·布雷多", "Joerg Bruemmer", "埃里克·布鲁威勒", "Dorian Bustamante", "埃蒙·巴特勒", "Howard Cabalfin", "Alex Cannon", "斯特凡·切雷蒂", "Pawasut Chatmaleerat", "蒂姆·克里斯滕森", "特伦特·克劳斯", "安德烈·柯林斯", "杰·库珀", "Laurent Cordier", "Brenton Cottman", "Ryan Cronin", "Steve Cronin", "Aaron Cubis", "Thiago Da Costa", "Andreas Dahn", "Ken Dailey", "罗汉·德赛", "Giovanni di Giulio", "Eric J. Dima-ala", "Lisa Theresa Downey-Dent", "Simeon Duncombe", "拉塞尔·厄尔", "Dan Enstrom", "Csaba László Eröss", "Katherine Farrar", "汤姆·菲杰斯", "Nathan Fok", "马克·O·福克", "David E. Franks", "Tonio Freitag", "阿曼·加洛", "Camille Geier", "Paul Ghezzo", "阿什拉弗·格尼姆", "斯温·吉尔伯格", "Neil Glasbey", "大卫·戈特利布", "Kritteka Gregory", "布兰科·格鲁契奇", "Greg Grusby", "Karen Halliwell", "迈克尔·哈尔斯特德", "保罗·哈林", "Dan Heder", "Jeff Higgins", "布鲁斯·霍尔科姆", "罗宾·霍兰德尔", "Katie Hooten", "Joe Howes", "Jonas Huerta", "Brett Ineson", "伊万·雅格布斯", "伊莱·贾拉", "Sven Jensen", "Chris Jestico", "Andreas Bravin Karlsson", "Shawn Kelly", "Connie Kennedy", "Doron Kipper", "Alex Knudsen", "Oliver Kurrle", "Mårten Larsson", "克里斯托弗·利尔蒙斯", "Alex Lemonis", "乔·莱特瑞", "Armando Lombardo", "Leah Low", "达米恩·马塞", "Carol Madrigal", "凯文·马泰尔", "David Masure-Bosco", "Robert McDougall", "Gurel Mehmet", "Szabolcs Menyhei", "Tory Mercer", "Steven Messing", "阿德里安·梅特泽拉尔", "Jacob Curtis Miller", "Lori C. Miller", "Oliver Money", "Mary Mullan", "Chris Munns", "Jeremy Nicolaides", "Peter Olliff", "凯利·波特", "蒂姆·波特", "Richard Pring", "Derek N. Prusak", "英德里普·拉哈", "Marco Revelant", "Diego Riestra", "Simone Riginelli", "格兰特·罗阿", "瑞安·D·罗梅罗", "埃隆·M·罗斯", "Emeric Saint-Germain", "卡罗·斯卡杜托", "Manos Scheto", "Eric Scott", "Steven J. Scott", "Luca Serafini", "戴恩·艾伦·史密斯", "道格·斯皮拉特罗", "Simon Stanley-Clamp", "András Szõcs", "Takashi Takeoka", "Justin Talley", "Ben Thompson", "Zelda Tinska", "Matthew Twyford", "Jen Underdahl", "贾斯汀·范·德·莱克", "John van Leeuwen", "阿曼多·贝拉斯克斯", "James William Visconti III", "Johan Walfridson", "Sean Noel Walker", "塔拉·沃克", "亚当·沃特斯", "戴维·温斯坦", "Dan Wheaton", "克里斯汀·王", "Mike Wood", "山口千代", "Marvyn Young", "Can Yuksel", "Matthias Zeller", "苏珊·佐曼", "Darren Bailey", "Jordi Cardus", "迈克·居坦", "Amanda Jane Porter", "Katri A. Vanhatalo", "付博文", "大卫·芬奇", "大卫·法默", "Josh Gold", "Scott Hinkley", "Daniel Laurie", "詹姆斯·利考斯基", "Brian Long", "Anele Morris", "香农·米尔斯", "丹·奥康奈尔", "李·奥尔洛夫", "Bryan Pennington", "Juan Peralta", "约翰·普里切特", "John Roesch", "布莱恩·桑德斯", "麦克·史密斯", "Vic Kaspar", "中西良太", "布赖恩·希契", "乔纳森·希克曼", "丹·阿布内特", "布莱恩·本迪斯", "埃里克·皮尔森", "爱德·布鲁贝克", "约翰·布西马", "约翰·伯恩", "Jim Cheung", "塔-内西·科茨", "吉因·科兰", "杰瑞·康威", "彼得·大卫", "Kelly Sue DeConnick", "史蒂夫·迪特寇", "Kieron Dwyer", "史蒂夫·恩格尔哈特", "Steve Epting", "大卫·芬奇", "Matt Fraction", "阿奇·古德温", "唐·赫克", "雷吉纳·哈德林", "安迪·兰宁", "鲍勃·莱顿", "斯坦·李", "拉里·利伯", "戴维·麦克法兰", "马克·米勒", "Carlo Pagulayan", "Greg Pak", "萨拉·皮凯利", "乔治·佩雷斯", "乔·奎萨达", "瑞克·雷蒙德", "唐·里科", "詹姆斯·罗宾逊", "小约翰·罗密塔", "沃尔特·西蒙森", "吉姆·斯特林", "罗杰·斯特恩", "罗伊·托马斯", "Jeffrey Steven Brink", "Jonathan Carbonaro", "Cory Clay", "Max Deleo", "Alessandro Di Meo", "Peter Drinco", "Jeremy Emerman", "Jeffrey Engelson", "Michael-Ryan Fletchall", "Jorge Luis German", "杰弗里·哈利", "Jason Kay", "Mitchell Andrew Lillian", "Maurice K. McGuire", "Saul McSween", "Justin Memovich", "Ryan Nguyen", "Lawrence Razo", "Dan Riffel", "Allen Christopher Robinson", "T. Daniel Scaringi", "Mike Shaw", "Devon Stinson", "Iain Thomson", "Mike Visencio", "盖伊·费尔南德斯", "萨拉·芬兰", "杰森·B·斯塔米", "埃里克·皮尔森", "山姆·哈格雷夫", "乔安·佩里塔诺", "莱斯利·波普", "亚伦·史维斯查", "迈克尔·格里洛", "Ted Alvarez", "Thomas Bowes", "Chris Cloud", "皮特·科宾", "James Lin", "Leila Nurse", "戴夫‧乔丹", "Clyde R. Maliauka", "Joel Marrow", "London Voices", "吉米·雷·皮肯斯", "Jon Mattox", "Claudia Rojas", "Trey Neely", "Perry Montague Mason", "The Newton Brothers", "马克·皮崔", "丹尼斯·S·桑兹", "亚伦·史维斯查", "James Thatcher", "基尔斯蒂·瓦利", "Anthony Almaraz", "Chris Armstrong", "Charles Alleneck", "Nicholas Bussey", "Valentina Aulisi", "James Corless", "杰森·B·斯塔米", "Justin Bertges", "Jason Blackman", "Peter S. Elliot", "Paul Ensby", "D.R. Farquharson", "MacKenzie Cleveland", "Alexander Gaeta", "Gray Marshall", "Carl McKay", "Tia Nolan", "Riki LeCotey", "斯蒂芬·索南菲尔德", "迈克·卢茨", "Heidi Tebo", "Jacqueline Martinez", "贾卡布·皮斯泰奇", "Lily Scott", "Jeff Vacanti", "Eilish Zebrasky", "Marija Juliette Abney", "Janeshia Adams-Ginyard", "George Alexander", "内特·安德拉德", "Christopher 'Critter' Antonucci", "兰达尔·阿切尔", "Steven Atkinson", "詹妮弗·巴杰", "Chris Balualua", "Danya Bateman", "Carrie Bernans", "Felix Betancourt", "朱万达斯·坎迪斯", "Janene Carleton", "Elisabeth P. Carpenter", "Courtney Chen", "阿尼斯·舍尔法", "费尔南多·简", "Tye Claybrook Jr.", "Thomas Joseph Culler", "Jahnel Curfman", "克里斯·丹尼尔斯", "Keith Davis", "Martin De Boer", "罗伯·德·格鲁特", "Justin Dobies", "Jayson Dumenigo", "Justin Eaton", "Jared S. Eddo", "Kiante Elam", "盖伊·费尔南德斯", "亚历桑德罗·福尔基托", "Colin Follenweider", "格伦·福斯特", "Shauna Galligan", "莫妮卡·甘德顿", "Khalid Ghajji", "Katrina Gelfand", "艾米丽塔·T·冈萨雷斯", "Dante Ha", "Garrett Hammond", "Jason Elwood Hanna", "鲍比·霍兰德·汉顿", "丹尼尔·哈格里夫", "山姆·哈格雷夫", "Regis Harrington", "赛尔·哈里斯", "Jim Hart", "Alexander Hashioka Oatfield", "Daniel Hernandez", "马克·希克斯", "Maria Hippolyte", "Crystal Hooks", "Lindsay Anne Hugghins", "Michael Hugghins", "詹姆斯·哈奇森三世", "莎拉·欧文", "Michael Jamorski", "Kirk A. Jenkins", "Precious Jenkins", "小弗洛伊德·安东尼·约翰", "Richard King", "Matt Laborde", "Danny Le Boyer", "麦特·伦纳德", "詹姆斯·卢", "瑞秋·鲁特雷尔", "Adam Lytle", "塔拉·麦肯", "Dave Macomber", "Ruben Maldonado", "Richard Marrero", "罗伯·马尔斯", "Anderson Martin", "海蒂·莫尼梅克", "雷妮·莫尼梅克", "Billy Morts", "玛莉·莫尔蒙", "Spencer Mulligan", "帕努瓦特·安东尼·纳纳肯帕诺姆", "John Nania", "Niko Nedyalkov", "Marque Ohmes", "Femi Olagoke", "Jane Oshita", "朴云龙", "Gary Peebles", "Josh Petro", "Lloyd Pitts", "格雷格·雷曼特", "Antjuan Rhames", "Michelle Rose", "Corrina Roshea", "埃琳娜·桑切斯", "迈克·史密斯", "Robert Daniel Souris", "杰克森斯·皮德尔", "Daniel Stevens", "Phedra Syndelle", "罗伯特·廷斯利", "阿隆·汤尼", "Anthony Vincent", "Tony Vo", "Todd Warren", "安伯·惠兰", "Joe Williams", "托姆·威廉姆斯", "Mike Wilson", "马库斯·杨", "Keil Oakley Zepernick", "卡梅隆·奥肯", "Karen Halliwell", "Peter Olliff", "马克·O·福克", "埃蒙·巴特勒", "Adam Blank", "Mary Mullan", "Johan Walfridson", "Ryan Cronin", "布鲁斯·霍尔科姆", "克里斯托弗·利尔蒙斯", "Steven J. Scott", "马特·艾特肯", "道格·斯皮拉特罗", "Gurel Mehmet", "Laurent Cordier", "Doron Kipper", "戴维·温斯坦", "Simon Stanley-Clamp", "Shawn Kelly", "埃里克·布鲁威勒", "Szabolcs Menyhei", "卢克·阿姆斯特朗", "米格尔·A·萨莱克", "保罗·阿里昂", "斯科特·埃德斯坦", "艾米丽·尼采", "陈安伟", "简·菲利普·克雷默", "保罗·哈林", "斯托恩·尼伦", "托马斯·尼特曼", "杰米·布莱斯", "丹尼·冈萨雷斯", "瑞秋·劳伦森", "特伦特·克劳斯", "卡迪尔·坎·埃克西", "瑞恩·赫斯蒂斯", "特伦特·牛顿", "布莱恩·J·阿尔瓦雷斯", "戴恩·艾伦·史密斯", "詹森·拉尼尔·布朗", "汉娜·龙", "卡洛斯·华达德", "罗恩·安德达尔", "Janeshia Adams-Ginyard", "George Alexander", "大卫·J·巴克", "内特·安德拉德", "David Boucher", "Christopher 'Critter' Antonucci", "兰达尔·阿切尔", "Jim Charmatz", "詹妮弗·巴杰", "Chris Balualua", "Danya Bateman", "Carrie Bernans", "Felix Betancourt", "达米安·费舍尔", "朱万达斯·坎迪斯", "Elisabeth P. Carpenter", "林赛·麦克戈温", "尚恩·马翰", "Tye Claybrook Jr.", "Thomas Joseph Culler", "Keith Davis", "Martin De Boer", "罗伯·德·格鲁特", "乔什·洛森", "Justin Dobies", "Jared S. Eddo", "盖伊·费尔南德斯", "Colin Follenweider", "格伦·福斯特", "丹尼尔·萨迪克", "Shauna Galligan", "莫妮卡·甘德顿", "Khalid Ghajji", "鲍比·霍兰德·汉顿", "丹尼尔·哈格里夫", "山姆·哈格雷夫", "Jim Hart", "Daniel Hernandez", "Maria Hippolyte", "Michael Hugghins", "詹姆斯·哈奇森三世", "Michael Jamorski", "Kirk A. Jenkins", "小弗洛伊德·安东尼·约翰", "麦特·伦纳德", "Adam Lytle", "塔拉·麦肯", "Dave Macomber", "海蒂·莫尼梅克", "Billy Morts", "玛莉·莫尔蒙", "Spencer Mulligan", "John Nania", "Niko Nedyalkov", "Marque Ohmes", "Jane Oshita", "朴云龙", "Gary Peebles", "Lloyd Pitts", "格雷格·雷曼特", "Michelle Rose", "Corrina Roshea", "Robert Daniel Souris", "杰克森斯·皮德尔", "Phedra Syndelle", "罗伯特·廷斯利", "阿隆·汤尼", "Anthony Vincent", "Tony Vo", "Todd Warren", "Joe Williams", "托姆·威廉姆斯", "Keil Oakley Zepernick", "卡梅隆·奥肯", "Anthony Almaraz", "Valentina Aulisi", "Justin Bertges", "Jason Blackman", "MacKenzie Cleveland", "Riki LeCotey", "迈克·卢茨", "Jacqueline Martinez", "Lily Scott", "Eilish Zebrasky", "Jacob Johnston", "Chris Armstrong", "Anthony Almaraz", "LaNease Adams", "亚伦·史维斯查", "布莱恩·安德鲁斯", "Demetrios Anastasiow", "Nicholas Bussey", "Thomas Bowes", "Valentina Aulisi", "James Corless", "Justin Bertges", "汤姆安东内利斯", "皮特·科宾", "布伦顿·科温顿", "Jason Blackman", "Richard Bennett", "Alexis Auditore", "Peter S. Elliot", "Paul Ensby", "Tony Bohorquez", "D.R. Farquharson", "MacKenzie Cleveland", "London Voices", "Clyde R. Maliauka", "Alexander Gaeta", "Joel Marrow", "Jon Mattox", "罗恩·博蒂塔", "Susan A. Burig", "Perry Montague Mason", "The Newton Brothers", "Qualen Bradley", "Claudia Rojas", "Gray Marshall", "马克·皮崔", "Jason Chalmers", "Carl McKay", "Ray Chan", "丹尼斯·S·桑兹", "Tia Nolan", "克雷·钱柏林", "James Thatcher", "James R. Walker", "基尔斯蒂·瓦利", "Cara Chooljian", "Riki LeCotey", "斯蒂芬·索南菲尔德", "Angie Lee Cobbs", "Jacqueline Martinez", "Heidi Tebo", "Nancy Deren", "Jeff Vacanti", "Ryan Shovey", "Ryan D'Silva", "Lily Scott", "Thomas Deming-Henes", "Tim Flattery", "Eckart Friz", "Kimberly Domínguez", "Eilish Zebrasky", "Chase Dunnette", "Adi Granov", "Theresa Greene", "Sean Hargreaves", "Skylar Felton", "Cory Fleming", "Rachael Lin Gallaghan", "Robert 'Rock' Galotti", "Martin Garner", "罗伯特·安德鲁·约翰逊", "Jade Gordon", "Ian Joyner", "安东尼·伦纳迪三世", "Addison Henderson", "Jerad Marantz", "Karl J. Martin", "Benjamin Holden", "Ron Mason", "Masako Masuda", "Iain McCaig", "Allan McKay", "Ryan Meinerding", "安德鲁·杰克", "Jeffrey Mossa", "Sonny Nguyen", "Cody Lassiter", "Kyle S. Plowden", "Andrew Reeder", "Eli Logue", "罗伯特·萨肯蒂", "Jill Rytie Lutz", "Phil Saunders", "Jim Stubblefield", "Tully Summers", "Cleo Wang", "Shaun Young", "哈里森·奥斯特菲尔德", "杰克森斯·皮德尔", "Isaac Phillips", "阿隆·汤尼", "本·普罗斯基", "安伯·惠兰", "Joe Williams", "托姆·威廉姆斯", "Kim Ronstadt", "马库斯·杨", "卡梅隆·奥肯", "Eli Sasich", "Christian J. Simpson", "Jim Templar", "Elizabeth Tyson", "Lukas Valderrama", "Alexandar Wagner", "Payton White", "Rebecca Whiting", "Jeff Willis", "克里斯托弗·瑞安·温特斯", "Matthew Rhode"], "rate": 9.1, "rate_num": 1923000.0, "money": 4250000000.0}