{"name_zh": "断背山", "name_en": "Brokeback Mountain", "categorys": ["剧情", "爱情", "家庭"], "area": "美国,加拿大", "duration": "134分钟", "date": "2005-09-02意大利上映", "awards": ["第78届奥斯卡金像奖", "第62届威尼斯电影节", "第78届奥斯卡金像奖", "第62届威尼斯电影节", "第63届金球奖", "第18届欧洲电影奖", "第59届英国电影学院奖", "第32届法国电影凯撒奖", "第15届MTV电影奖", "第51届意大利大卫奖", "第21届独立精神奖", "第9届好莱坞电影奖", "第45届美国剪辑工会奖", "第70届纽约影评人协会奖", "第58届美国导演工会奖", "第12届美国演员工会奖", "第6届美国电影学会奖"], "director": "李安", "actors": ["希斯·莱杰", "杰克·吉伦哈尔", "米歇尔·威廉姆斯", "兰迪·奎德", "李安", "希斯·莱杰", "杰克·吉伦哈尔", "米歇尔·威廉姆斯", "兰迪·奎德", "安妮·海瑟薇", "凯特·玛拉", "格拉汉姆·贝克尔", "大卫·哈伯", "罗伯塔·马克斯韦尔", "皮特·麦克罗比", "安娜·法瑞丝", "琳达·卡德里尼", "Tyson Wiebe", "Jayson Therrien", "罗德里格·普列托", "Mary McBride", "Jon-Paul Khouri", "Cam Sutherland", "Christian Fraser", "Gary Lauder", "Will Martin", "杰克·丘奇", "夏恩·希尔", "Cayla Wolever", "Jerry Callaghan", "Jacey Kenny", "Pete Seadon", "Keanna Dubé", "Steffen Cole Moser", "Kade Philps", "Mary Liboiron", "Dean Barrett", "Duval Lang", "Don Bland", "Dan McDougall", "Lachlan Mackintosh", "Victor Reyes", "David Trimble", "艾瑞卡·沃尔特", "凯林·西", "肯·罗伯茨", "巴布·米切尔", "约翰·腾奇", "Ken Zilka", "Sarah Hyslop", "James Baker", "布鲁克琳·普劳克斯", "斯科特·迈克尔·坎贝尔", "Hannah Stewart", "史蒂文·克里·莫利森", "汤姆·凯瑞", "马蒂·安东尼尼", "瓦莱丽·普朗什", "Larry Reese", "戴夫·特里布尔", "大卫·达斯马齐连", "萝伯塔·麦斯威尔", "Tom Carey", "Ken Roberts", "Kade Phillips", "安妮·普劳克丝", "拉里·麦克穆特瑞", "黛安娜·奥撒纳", "安妮·普鲁", "詹姆士·沙姆斯", "迈克尔·考斯提甘", "Tom Cox", "Scott Ferguson", "迈克尔·豪斯曼", "Murray Ord", "Jordy Randall", "黛安娜·奥撒纳", "拉里·麦克穆特瑞", "比尔·波拉德", "罗德里格·普列托", "罗德里格·普列托", "Laura Ballinger", "Tracey Baryski", "朱迪·贝克尔", "杰拉丁·佩罗尼", "迪伦·蒂奇纳", "Cody Klepper", "古斯塔沃·桑多拉拉", "古斯塔沃·桑多拉拉", "Anibal Kerpel", "Annette Kudrak", "马塞洛·扎尔沃斯", "Kory Kruckenberg", "William V. Malpede", "Travis McConnell", "Brad Moerke", "Katherine Ringer", "皮埃尔·特伦布莱", "迈克尔·豪斯曼", "朱迪·贝克尔", "马利特·艾伦", "曼奥·罗切蒂", "琳达·梅拉佐", "Penny Thompson", "路易斯·莫林", "Bruno-Olivier Laflamme", "马克·特拉斯科", "Sarah Coatts", "Kam Chan", "Marko A. Costanzo", "尤金·吉尔蒂", "肯顿·贾卡布", "Frank Kern", "德鲁·库宁", "George A. Lara", "Geo Major", "Igor Nikolic", "雷利·斯蒂尔", "菲利普·斯托克顿", "David Warzynski", "安迪·赖特", "Wyatt Sprague", "里克·加西亚", "亚利桑德罗·冈萨雷斯·伊纳里图", "路易斯·莫林", "杰拉丁·佩罗尼", "古斯塔沃·桑多拉拉", "David Vernerey", "Kirk Chiswell", "Chris Kosloski", "Corey Lee", "Christopher G. Sprague", "Peter Wunstorf", "Stephen Osborn", "艾薇·考夫曼", "Deb Green", "Jessica Daniels", "Tom Benz", "Gerry Robert Byrne", "Scott Ferguson", "古斯塔沃·桑多拉拉", "Cody Klepper", "T.J. Bews", "Lynn Ivall", "Kirk Jarrett", "格雷 施洛瑟", "Christian Fraser", "Ken Zilka", "Lynn Ivall", "Kirk Jarrett", "T.J. Bews", "格雷 施洛瑟", "Krishna Ribeiro", "Anibal Kerpel", "Annette Kudrak", "Krishna Ribeiro", "Val Brown", "Lawrence Howard Williams", "马塞洛·扎尔沃斯", "Colt Hausman", "Kory Kruckenberg", "Hudson Cooley", "William V. Malpede", "Charmaine Husum", "Kurt Enger", "Jay Floyd", "Samuel V. Franco", "Evan Godfrey", "Annie Hannan", "Steven Hanulik", "Sara Ossana", "Kirk Jarrett", "Ron Landry", "Catherine McGovern", "Naomi Robinson", "Sheila Thomas", "Jamie Switch", "Christopher Tricarico", "James Tyce", "David Benning", "斯蒂芬·布吉格沃特", "Flax Glor", "Christine Kilpatrick", "Timothy Schwalk"], "rate": 8.9, "rate_num": 1040.0, "money": -1}